pybind11_numpy_example-1.0.1.dist-info/METADATA
pybind11_numpy_example-1.0.1.dist-info/RECORD
pybind11_numpy_example-1.0.1.dist-info/WHEEL
pybind11_numpy_example-1.0.1.dist-info/licenses/LICENSE.md
pybind11_numpy_example/python_code.py
pybind11_numpy_example/__init__.py
pybind11_numpy_example/_pybind11_numpy_example.cpython-39-x86_64-linux-gnu.so
