Metadata-Version: 2.1
Name: pybind11-numpy-example
Version: 1.0.1
Summary: An example of using numpy with pybind11
Keywords: pybind11,cibuildwheel,c++,pypi,numpy,simple,example,wheel,pypi,conda-forge
Author-Email: Liam Keegan <liam@keegan.ch>
Maintainer-Email: Liam Keegan <liam@keegan.ch>
License: MIT
Classifier: Programming Language :: C++
Classifier: Programming Language :: Python :: 3 :: Only
Classifier: Programming Language :: Python :: 3.8
Classifier: Programming Language :: Python :: 3.9
Classifier: Programming Language :: Python :: 3.10
Classifier: Programming Language :: Python :: 3.11
Classifier: Programming Language :: Python :: 3.12
Classifier: Programming Language :: Python :: 3.13
Classifier: Programming Language :: Python :: Implementation :: CPython
Classifier: Programming Language :: Python :: Implementation :: PyPy
Classifier: Operating System :: MacOS :: MacOS X
Classifier: Operating System :: Microsoft :: Windows
Classifier: Operating System :: POSIX :: Linux
Classifier: License :: OSI Approved :: MIT License
Project-URL: Github, https://github.com/ssciwr/pybind11-numpy-example
Project-URL: Documentation, https://pybind11-numpy-example.readthedocs.io
Requires-Python: >=3.8
Requires-Dist: numpy
Requires-Dist: pytest; extra == "test"
Requires-Dist: cmake; extra == "docs"
Requires-Dist: breathe; extra == "docs"
Requires-Dist: sphinx_rtd_theme; extra == "docs"
Provides-Extra: test
Provides-Extra: docs
